superhash
