Metadata-Version: 1.0
Name: SuperHash
Version: 0.1.2
Summary: Hash anything
Home-page: https://github.com/uniphil/SuperHash
Author: Philip Schleihauf
Author-email: uniphil@gmail.com
License: GPLv3
Platform: UNKNOWN
